muscletraining.py
muscletraining-0.0.3.dist-info/METADATA
muscletraining-0.0.3.dist-info/WHEEL
muscletraining-0.0.3.dist-info/entry_points.txt
muscletraining-0.0.3.dist-info/top_level.txt
muscletraining-0.0.3.dist-info/RECORD
