Metadata-Version: 2.1
Name: muscletraining
Version: 0.0.3
Summary: Package to determine arm extension and contraction
Home-page: https://github.com/awayaniina/muscle-training
Author: niina awaya
Author-email: s2122003@stu.musashino-u.ac.jp
Project-URL: Bug Tracker, https://github.com/awayaniina/muscle-training
Classifier: Programming Language :: Python :: 3
Classifier: License :: OSI Approved :: MIT License
Classifier: Operating System :: OS Independent
Requires-Python: >=3.7
